my_datasets_lib/__init__.py
my_datasets_lib/data/atu_clean.csv
my_datasets_lib/data/atu_dirty.csv
my_datasets_lib/data/cdc.csv
my_datasets_lib/data/food_ids.csv
my_datasets_lib/data/timeuse_ids.csv
my_datasets_lib/data/timeuse_ids_clean.csv
my_datasets_lib/datasets/__init__.py
my_datasets_lib/datasets/atu_clean.py
my_datasets_lib/datasets/atu_dirty.py
my_datasets_lib/datasets/cdc.py
my_datasets_lib/datasets/food_ids.py
my_datasets_lib/datasets/timeuse_ids.py
my_datasets_lib/datasets/timeuse_ids_clean.py
my_datasets_lib-0.93.dist-info/METADATA
my_datasets_lib-0.93.dist-info/WHEEL
my_datasets_lib-0.93.dist-info/top_level.txt
my_datasets_lib-0.93.dist-info/RECORD
